<?xml version="1.0" encoding="utf-8"?>
<Entity parent="template_unit_hero_infantry_spearman">

  <Identity>
    <Civ>anish</Civ>
    <GenericName></GenericName>
    <SpecificName></SpecificName>
    <VisibleClasses datatype="tokens">Guerilla</VisibleClasses>
    <SelectionGroupName>units/anish/hero_jaguar_king</SelectionGroupName>
    <Icon>units/zapo/hero_lord_jaguar.png</Icon>
  </Identity>
  <UnitMotion>
    <WalkSpeed op="mul">1.5</WalkSpeed>
  </UnitMotion>
  <VisualActor>
    <Actor>units/anishinaabe/infantry_champion_clubman.xml</Actor>
  </VisualActor>
</Entity>
