<?xml version="1.0" encoding="utf-8"?>
<Entity parent="template_unit_champion_infantry_spearman">
  <Identity>
    <Civ>kartl</Civ>
    <GenericName>Thracian Hoplite</GenericName>
    <SpecificName/>
    <Icon>units/thra/champion_infantry_spearman.png</Icon>
    <Requirements>
      <Techs datatype="tokens">
        -phase_city
        unlock_champion_infantry
      </Techs>
    </Requirements>
  </Identity>
  <VisualActor>
    <Actor>units/thracians/infantry_spearman_c.xml</Actor>
  </VisualActor>
</Entity>
