<?xml version="1.0" encoding="utf-8"?>
<actor version="1">
  <castshadow/>
  <group>
    <variant frequency="1" name="a1">
      <mesh>props/hair/mochica/hair_fem_moch_01.dae</mesh>
    </variant>
    <variant frequency="1" name="a2">
      <mesh>props/hair/mochica/hair_fem_moch_02.dae</mesh>
    </variant>
    <variant frequency="1" name="a3">
      <mesh>props/hair/mochica/hair_fem_moch_03.dae</mesh>
    </variant>
  </group>
  <group>
    <variant frequency="1" name="face-a">
      <textures><texture file="props/head/zapo_fem_deco.png" name="baseTex"/></textures>
    </variant>
  </group>
  <group>
    <variant frequency="1" name="hair-dark brown">
      <color>75 61 38</color>
    </variant>
  </group>
  <material>objectcolor.xml</material>
</actor>